MANIFEST.in
README.md
setup.py
tvtid.py
tvtid.egg-info/PKG-INFO
tvtid.egg-info/SOURCES.txt
tvtid.egg-info/dependency_links.txt
tvtid.egg-info/entry_points.txt
tvtid.egg-info/requires.txt
tvtid.egg-info/top_level.txt