Metadata-Version: 1.2
Name: tvtid
Version: 0.2.1
Summary: Library and cli tool for querying tvtid.dk
Home-page: https://github.com/kirkegaard/tvtid.py
Author: Christian Kirkegaard
Author-email: christian@lowpoly.dk
License: MIT
Download-URL: https://github.com/kirkegaard/tvtid.py
Platform: UNKNOWN
Classifier: Environment :: X11 Applications
Classifier: License :: OSI Approved :: MIT License
Classifier: Operating System :: POSIX :: Linux
Classifier: Programming Language :: Python :: 3.5
Classifier: Programming Language :: Python :: 3.6
Requires-Python: >=3.5
